amplia_client/__init__.py
amplia_client/amplia_error.py
amplia_client/arisp_roles.py
amplia_client/base_certificate.py
amplia_client/base_order.py
amplia_client/certificate.py
amplia_client/certificate_formats.py
amplia_client/certificate_kinds.py
amplia_client/certificate_parameters.py
amplia_client/certificate_summary.py
amplia_client/client.py
amplia_client/create_order_request.py
amplia_client/issue_certificate_request.py
amplia_client/name.py
amplia_client/order.py
amplia_client/order_locked_error.py
amplia_client/order_status.py
amplia_client/paginated_search_params.py
amplia_client/paginated_search_response.py
amplia_client/pagination_orders.py
amplia_client/rest_base_error.py
amplia_client/rest_client.py
amplia_client/rest_error.py
amplia_client/rest_unreachable_error.py
amplia_client-1.0.0.dist-info/METADATA
amplia_client-1.0.0.dist-info/RECORD
amplia_client-1.0.0.dist-info/WHEEL
amplia_client-1.0.0.dist-info/top_level.txt
